scDB/CCG.py
scDB/EGA.py
scDB/__init__.py
scDB/argParser.py
scDB/db.py
scDB-0.0.1.data/scripts/scDB
scDB-0.0.1.dist-info/METADATA
scDB-0.0.1.dist-info/WHEEL
scDB-0.0.1.dist-info/top_level.txt
scDB-0.0.1.dist-info/RECORD
