Metadata-Version: 2.1
Name: scDB
Version: 0.0.1
Summary: single cell database utilities
Home-page: https://jingxinfu.github.io/scDB
Author: Jingxin Fu
Author-email: jingxinfu.tj@gmail.com
License: UNKNOWN
Keywords: single cell,terra
Platform: UNKNOWN
Classifier: Programming Language :: Python :: 3
Classifier: License :: OSI Approved :: GNU General Public License v3 or later (GPLv3+)
Classifier: Operating System :: OS Independent
Requires-Python: >=3.4, <4
Requires-Dist: firecloud
Requires-Dist: tenacity
Requires-Dist: pandas
Requires-Dist: colorlog
